CHANGELOG.rst
MANIFEST.in
README.rst
setup.py
plone/__init__.py
plone.app.deco.egg-info/PKG-INFO
plone.app.deco.egg-info/SOURCES.txt
plone.app.deco.egg-info/dependency_links.txt
plone.app.deco.egg-info/entry_points.txt
plone.app.deco.egg-info/namespace_packages.txt
plone.app.deco.egg-info/not-zip-safe
plone.app.deco.egg-info/requires.txt
plone.app.deco.egg-info/top_level.txt
plone/app/__init__.py
plone/app/deco/__init__.py
plone/app/deco/bbb.py
plone/app/deco/bbb.zcml
plone/app/deco/configure.zcml
plone/app/deco/interfaces.py
plone/app/deco/registry.txt
plone/app/deco/testing.py
plone/app/deco/toolbar.pt
plone/app/deco/utils.py
plone/app/deco/profiles/bbb/metadata.xml
plone/app/deco/profiles/bbb/viewlets.xml
plone/app/deco/profiles/default/browserlayer.xml
plone/app/deco/profiles/default/controlpanel.xml
plone/app/deco/profiles/default/cssregistry.xml
plone/app/deco/profiles/default/jsregistry.xml
plone/app/deco/profiles/default/metadata.xml
plone/app/deco/profiles/default/registry.xml
plone/app/deco/profiles/default/rolemap.xml
plone/app/deco/resources/default_tile_icon.png
plone/app/deco/resources/examples.html
plone/app/deco/resources/index.html
plone/app/deco/resources/tile-icons.png
plone/app/deco/resources/demo/index.html
plone/app/deco/resources/demo/logo.png
plone/app/deco/resources/demo/main.css
plone/app/deco/resources/demo/reset.css
plone/app/deco/resources/lib/jquery-1.6.4.js
plone/app/deco/resources/lib/jquery.event.drag-2.1.0.js
plone/app/deco/resources/lib/jquery.event.drop-2.1.0.js
plone/app/deco/resources/lib/jquerytools.expose-1.2.6.js
plone/app/deco/resources/src/deco.css
plone/app/deco/resources/src/deco.js
plone/app/deco/resources/src/plone.deco.js
plone/app/deco/resources/tests/index.html
plone/app/deco/resources/tests/jquery.mockjax.js
plone/app/deco/resources/tests/phantomjs_qunit.js
plone/app/deco/resources/tests/qunit.css
plone/app/deco/resources/tests/qunit.js
plone/app/deco/resources/tests/test_deco.js
plone/app/deco/tests/__init__.py
plone/app/deco/tests/jsTestDriver.conf
plone/app/deco/tests/registry_testdata.py
plone/app/deco/tests/test_browser_decoconfig.txt
plone/app/deco/tests/test_decoregistry.py
plone/app/deco/tests/test_doctest.py
plone/app/deco/tests/test_layout_widget.txt
plone/app/deco/tests/test_widget.py
