Metadata-Version: 1.0
Name: plone.app.deco
Version: 1.0
Summary: Package for Deco UI functionality
Home-page: https://github.com/plone/plone.app.deco
Author: Rob Gietema
Author-email: rob@fourdigits.nl
License: GPL
Keywords: deco plone editor toolbar
Platform: UNKNOWN
Classifier: Framework :: Plone
Classifier: Programming Language :: Python
Classifier: Topic :: Software Development :: Libraries :: Python Modules
